flask_gws/__init__.py
flask_gws/__version__.py
flask_gws/_uwsgi.py
flask_gws/websocket.py
flask_gws-0.1.0.dist-info/LICENSE
flask_gws-0.1.0.dist-info/WHEEL
flask_gws-0.1.0.dist-info/METADATA
flask_gws-0.1.0.dist-info/RECORD
