Metadata-Version: 2.1
Name: flask-gws
Version: 0.1.0
Summary: High-performance WebSockets for Flask apps powered by uWSGI and gevent
Author-email: Nidal Alhariri <level09@gmail.com>
Requires-Python: >=3.7
Classifier: Development Status :: 4 - Beta
Classifier: Framework :: Flask
Classifier: Intended Audience :: Developers
Classifier: License :: OSI Approved :: MIT License
Classifier: Programming Language :: Python :: 3
Classifier: Programming Language :: Python :: 3.7
Classifier: Programming Language :: Python :: 3.8
Classifier: Programming Language :: Python :: 3.9
Classifier: Programming Language :: Python :: 3.10
Classifier: Programming Language :: Python :: 3.11
Classifier: Programming Language :: Python :: 3.12
Classifier: Topic :: Internet :: WWW/HTTP :: WSGI
Classifier: Topic :: Software Development :: Libraries :: Python Modules
Requires-Dist: Flask>=2.0.0
Requires-Dist: gevent>=22.10.2
Requires-Dist: uwsgi>=2.0.0 ; extra == "uwsgi"
Project-URL: Homepage, https://github.com/level09/flask-gws
Project-URL: Issues, https://github.com/level09/flask-gws/issues
Provides-Extra: uwsgi
